requestwrapper/Request.py
requestwrapper/__init__.py
requestwrapper-0.0.5.dist-info/LICENSE
requestwrapper-0.0.5.dist-info/METADATA
requestwrapper-0.0.5.dist-info/WHEEL
requestwrapper-0.0.5.dist-info/top_level.txt
requestwrapper-0.0.5.dist-info/RECORD
