Metadata-Version: 2.1
Name: requestwrapper
Version: 0.0.5
Summary: A simple wrapper for the requests package
Home-page: https://github.com/jskroodsma
Author: J.S. Kroodsma
Author-email: j.s.kroodsma@gmail.com
License: UNKNOWN
Platform: UNKNOWN
Classifier: Programming Language :: Python :: 3
Classifier: License :: OSI Approved :: MIT License
Classifier: Operating System :: OS Independent
Requires-Python: >=3.6
